Workbook
Name 南: 天板換算表!$D$3:$D$46
Name 南: 販売表!$C$5:$C$44

Sheet 商品マスタ
A1: ID | B1: 商品名 | C1: 単価 | D1: 限界利益単価 | E1: 1箱当たりの入数 | F1: ラベル包装階 | G1: 注文数倍数 | H1: 店売り数
A2: 1 | B2: 商品A | C2: 155 | D2: 91.34 | E2: 7 | F2: 1
A3: 2 | B3: 商品B | C3: 163 | D3: 107.04 | E3: 15 | F3: 1 | G3: 3
A4: 3 | B4: 商品C(バリエーション1) | C4: 149 | D4: 90.77 | E4: 12 | F4: 1 | G4: 4 | H4: 0
A5: 4 | B5: 商品C(バリエーション2) | C5: 149 | D5: 90.77 | E5: 12 | F5: 1 | G5: 4 | H5: 0
A6: 5 | B6: 商品C(バリエーション3) | C6: 149 | D6: 90.77 | E6: 12 | F6: 1 | G6: 4 | H6: 0
A7: 6 | B7: 商品C(バリエーション4) | C7: 149 | D7: 90.77 | E7: 12 | F7: 1 | G7: 4 | H7: 0
A8: 7 | B8: 商品D | C8: 200 | D8: 122.95 | E8: 12 | F8: 2 | G8: 3
A9: 8 | B9: 商品E | C9: 188 | D9: 109.07 | E9: 6 | F9: 2 | G9: 2
A10: 9 | B10: 商品F | C10: 190 | D10: 101.32 | E10: 9 | F10: 2 | G10: 2
A11: 10 | B11: 商品G | C11: 137 | D11: 93.31 | E11: 9 | F11: 2 | G11: 2
A12: 11 | B12: 商品H | C12: 137 | D12: 90.06 | E12: 6 | F12: 1 | G12: 4
A13: 12 | B13: 商品I | C13: 175 | D13: 105.77 | E13: 12 | F13: 1
A14: 13 | B14: 商品J | C14: 183 | D14: 114.225 | E14: 12 | F14: 1
A15: 14 | B15: 商品K | C15: 146 | D15: 94.44 | E15: 20 | F15: 1 | G15: 5
A16: 15 | B16: 商品L | C16: 210 | D16: 204 | E16: 9 | F16: 2 | G16: 2 | H16: 4
A17: 16 | B17: 商品M | C17: 190 | D17: 185 | E17: 12 | F17: 2 | G17: 1 | H17: 0
A18: 17 | B18: 商品N | C18: 120 | D18: 115 | E18: 15 | F18: 1 | G18: 4 | H18: 0
A19: 18 | B19: 商品O | C19: 200 | D19: 143.4 | E19: 7 | F19: 2 | G19: 2 | H19: 3
A20: 19 | B20: 商品P | C20: 210 | D20: 152.9 | E20: 7 | F20: 2 | G20: 2 | H20: 3

Sheet 販売表
B1: 販売表
B3: 総合計 | C3: 営業所A | D3: 営業所B | E3: 営業所C | F3: 営業所D | G3: 営業所E
B4: =SUM(C4:G4) -> 0
B5: =SUM(C5:G5) -> 0
B6: =SUM(C6:G6) -> 0
B7: =SUM(C7:G7) -> 0
B8: =SUM(C8:G8) -> 0
B9: =SUM(C9:G9) -> 0
B10: =SUM(C10:G10) -> 0 | I10: 日付変更
B11: =SUM(C11:G11) -> 0 | I11: 野菜ロール確認
B12: =SUM(C12:G12) -> 0 | I12: 店舗を確認
B13: =SUM(C13:G13) -> 0 | I13: 注文数チェックする | N13: ↓社長のいるところ、レジ横の製造
B14: =SUM(C14:G14) -> 0 | I14: プリントについて | K14: ＊白の日→ | L14: 南からの表 | M14: 6枚 | N14: （１階製造 ２枚/ﾚｼﾞ１枚/シールラベルチェック用１枚）
B15: =SUM(C15:G15) -> 0 | N15: （２階２枚）
B16: =SUM(C16:G16) -> 0 | N16: （３階事務所）
B17: =SUM(C17:G17) -> 0 | L17: 和歌山からの表 2枚 | N17: (１階シールラベルチェック表１枚)
B18: =SUM(C18:G18) -> 0 | N18: （２階１枚）
B19: =SUM(C19:G19) -> 0 | N19: (3階事務所
B20: =SUM(C20:G20) -> 0 | K20: ＊みどり→南からの表のうち３枚を緑に１階製造 ２枚/ﾚｼﾞ１枚
B21: =SUM(C21:G21) -> 0
B22: =SUM(C22:G22) -> 0 | K22: 箱数計算書 １枚(2F)
B23: =SUM(C23:G23) -> 0
B24: =SUM(C24:G24) -> 0
B25: =SUM(C25:G25) -> 0
B26: =SUM(C26:G26) -> 0
B27: =SUM(C27:G27) -> 0
B28: =SUM(C28:G28) -> 0
B29: =SUM(C29:G29) -> 0
B30: =SUM(C30:G30) -> 0
B31: =SUM(C31:G31) -> 0
B32: =SUM(C32:G32) -> 0
B33: =SUM(C33:G33) -> 0
B34: =SUM(C34:G34) -> 0
... B57: =SUM(C57:G57) -> 0
A58: 合 計 | B58: =SUM(B4:B57) -> 0 | C58: =SUM(C4:C57) -> 0 | D58: =SUM(D4:D57) -> 0 | E58: =SUM(E4:E57) -> 0 | F58: =SUM(F4:F57) -> 0 | G58: =SUM(G4:G57) -> 0
C59: =C3 -> 営業所A | D59: =D3 -> 営業所B | E59: =E3 -> 営業所C | F59: =F3 -> 営業所D | G59: =G3 -> 営業所E

Sheet 箱数計算書
A1: 箱数計算書 | C1: =販売表!A1 -> 0 | F1: 販売分
A3: 品 名 | B3: =販売表!C3 -> 営業所A | C3: =販売表!D3 -> 営業所B | D3: =販売表!E3 -> 営業所C | E3: =販売表!F3 -> 営業所D | F3: =販売表!G3 -> 営業所E
A4: =IF(販売表!A4=0,"",販売表!A4) | B4: =換算１!D4 | C4: =換算１!F4 | D4: =換算１!H4 | E4: =換算１!J4 | F4: =換算１!L4
A5: =IF(販売表!A5=0,"",販売表!A5) | B5: =換算１!D5 | C5: =換算１!F5 | D5: =換算１!H5 | E5: =換算１!J5 | F5: =換算１!L5
A6: =IF(販売表!A6=0,"",販売表!A6) | B6: =換算１!D6 | C6: =換算１!F6 | D6: =換算１!H6 | E6: =換算１!J6 | F6: =換算１!L6
A7: =IF(販売表!A7=0,"",販売表!A7) | B7: =換算１!D7 | C7: =換算１!F7 | D7: =換算１!H7 | E7: =換算１!J7 | F7: =換算１!L7
A8: =IF(販売表!A8=0,"",販売表!A8) | B8: =換算１!D8 | C8: =換算１!F8 | D8: =換算１!H8 | E8: =換算１!J8 | F8: =換算１!L8
A9: =IF(販売表!A9=0,"",販売表!A9) | B9: =換算１!D9 | C9: =換算１!F9 | D9: =換算１!H9 | E9: =換算１!J9 | F9: =換算１!L9
A10: =IF(販売表!A10=0,"",販売表!A10) | B10: =換算１!D10 | C10: =換算１!F10 | D10: =換算１!H10 | E10: =換算１!J10 | F10: =換算１!L10
A11: =IF(販売表!A11=0,"",販売表!A11) | B11: =換算１!D11 | C11: =換算１!F11 | D11: =換算１!H11 | E11: =換算１!J11 | F11: =換算１!L11
A12: =IF(販売表!A12=0,"",販売表!A12) | B12: =換算１!D12 | C12: =換算１!F12 | D12: =換算１!H12 | E12: =換算１!J12 | F12: =換算１!L12
A13: =IF(販売表!A13=0,"",販売表!A13) | B13: =換算１!D13 | C13: =換算１!F13 | D13: =換算１!H13 | E13: =換算１!J13 | F13: =換算１!L13
A14: =IF(販売表!A14=0,"",販売表!A14) | B14: =換算１!D14 | C14: =換算１!F14 | D14: =換算１!H14 | E14: =換算１!J14 | F14: =換算１!L14
A15: =IF(販売表!A15=0,"",販売表!A15) | B15: =換算１!D15 | C15: =換算１!F15 | D15: =換算１!H15 | E15: =換算１!J15 | F15: =換算１!L15
... A39: =IF(販売表!A39=0,"",販売表!A39) | B39: =換算１!D39 | C39: =換算１!F39 | D39: =換算１!H39 | E39: =換算１!J39 | F39: =換算１!L39
A40: =IF(販売表!A40=0,"",販売表!A40) | B40: =換算１!D40 | C40: =換算１!F40 | D40: =換算１!H40 | E40: =換算１!J40 | F40: =換算１!L40 | H40: 7
A41: =IF(販売表!A41=0,"",販売表!A41) | B41: =換算１!D41 | C41: =換算１!F41 | D41: =換算１!H41 | E41: =換算１!J41 | F41: =換算１!L41
A42: =IF(販売表!A42=0,"",販売表!A42) | B42: =換算１!D42 | C42: =換算１!F42 | D42: =換算１!H42 | E42: =換算１!J42 | F42: =換算１!L42
A43: =IF(販売表!A43=0,"",販売表!A43) | B43: =換算１!D43 | C43: =換算１!F43 | D43: =換算１!H43 | E43: =換算１!J43 | F43: =換算１!L43
A44: =IF(販売表!A44=0,"",販売表!A44) | B44: =換算１!D44 | C44: =換算１!F44 | D44: =換算１!H44 | E44: =換算１!J44 | F44: =換算１!L44
A45: =IF(販売表!A45=0,"",販売表!A45) | B45: =換算１!D45 | C45: =換算１!F45 | D45: =換算１!H45 | E45: =換算１!J45 | F45: =換算１!L45
A46: =IF(販売表!A46=0,"",販売表!A46) | B46: =換算１!D46 | C46: =換算１!F46 | D46: =換算１!H46 | E46: =換算１!J46 | F46: =換算１!L46
A47: =IF(販売表!A47=0,"",販売表!A47) | B47: =換算１!D47 | C47: =換算１!F47 | D47: =換算１!H47 | E47: =換算１!J47 | F47: =換算１!L47
A48: =IF(販売表!A48=0,"",販売表!A48) | B48: =換算１!D48 | C48: =換算１!F48 | D48: =換算１!H48 | E48: =換算１!J48 | F48: =換算１!L48
A49: =IF(販売表!A49=0,"",販売表!A49) | B49: =換算１!D49 | C49: =換算１!F49 | D49: =換算１!H49 | E49: =換算１!J49 | F49: =換算１!L49
A50: =IF(販売表!A50=0,"",販売表!A50) | B50: =換算１!D50 | C50: =換算１!F50 | D50: =換算１!H50 | E50: =換算１!J50 | F50: =換算１!L50
A51: =IF(販売表!A51=0,"",販売表!A51) | B51: =換算１!D51 | C51: =換算１!F51 | D51: =換算１!H51 | E51: =換算１!J51 | F51: =換算１!L51
A52: =IF(販売表!A52=0,"",販売表!A52) | B52: =換算１!D52 | C52: =換算１!F52 | D52: =換算１!H52 | E52: =換算１!J52 | F52: =換算１!L52
... A57: =IF(販売表!A57=0,"",販売表!A57) | B57: =換算１!D57 | C57: =換算１!F57 | D57: =換算１!H57 | E57: =換算１!J57 | F57: =換算１!L57
A58: 合 計 | B58: =SUM(B4:B57) -> 0 | C58: =SUM(C4:C57) -> 0 | D58: =SUM(D4:D57) -> 0 | E58: =SUM(E4:E57) -> 0 | F58: =SUM(F4:F57) -> 0
B59: =B3 -> 営業所A | C59: =C3 -> 営業所B | D59: =D3 -> 営業所C | E59: =E3 -> 営業所D | F59: =F3 -> 営業所E
B60: 箱数合計 | D60: =SUM(B58:F58) -> 0

Sheet 天板換算表
A1: =販売表!A1 -> 0 | B1: 注文数チェック
B2: 注文総合計 | C2: 倍数 | D2: 店売り数 | E2: 総数 | F2: 鉄板の個数 | G2: 換算鉄板数 | H2: 鉄板数 | I2: 余り
A3: =IF(販売表!A4=0,"",販売表!A4) | B3: =IF(A3="","",販売表!B4) | E3: =IF(A3="","",B3*C3+D3)
A4: =IF(販売表!A5=0,"",販売表!A5) | B4: =IF(A4="","",販売表!B5) | E4: =IF(A4="","",B4*C4+D4)
A5: =IF(販売表!A6=0,"",販売表!A6) | B5: =IF(A5="","",販売表!B6) | E5: =IF(A5="","",B5*C5+D5)
A6: =IF(販売表!A7=0,"",販売表!A7) | B6: =IF(A6="","",販売表!B7) | E6: =IF(A6="","",B6*C6+D6)
A7: =IF(販売表!A8=0,"",販売表!A8) | B7: =IF(A7="","",販売表!B8) | E7: =IF(A7="","",B7*C7+D7)
A8: =IF(販売表!A9=0,"",販売表!A9) | B8: =IF(A8="","",販売表!B9) | E8: =IF(A8="","",B8*C8+D8)
A9: =IF(販売表!A10=0,"",販売表!A10) | B9: =IF(A9="","",販売表!B10) | E9: =IF(A9="","",B9*C9+D9)
A10: =IF(販売表!A11=0,"",販売表!A11) | B10: =IF(A10="","",販売表!B11) | E10: =IF(A10="","",B10*C10+D10)
A11: =IF(販売表!A12=0,"",販売表!A12) | B11: =IF(A11="","",販売表!B12) | E11: =IF(A11="","",B11*C11+D11)
A12: =IF(販売表!A13=0,"",販売表!A13) | B12: =IF(A12="","",販売表!B13) | E12: =IF(A12="","",B12*C12+D12)
A13: =IF(販売表!A14=0,"",販売表!A14) | B13: =IF(A13="","",販売表!B14) | E13: =IF(A13="","",B13*C13+D13)
A14: =IF(販売表!A15=0,"",販売表!A15) | B14: =IF(A14="","",販売表!B15) | E14: =IF(A14="","",B14*C14+D14)
... A56: =IF(販売表!A57=0,"",販売表!A57) | B56: =IF(A56="","",販売表!B57) | E56: =IF(A56="","",B56*C56+D56)
A57: 合 計 | B57: =SUM(B3:B48) -> 0 | E57: =SUM(E3:E48) -> 0

Sheet 換算１
A1: 箱数換算表 | B1: =販売表!A1 -> 0 | F1: 販売分
A3: 品 名 | B3: １箱の個数 | C3: A換算数 | D3: A箱数 | E3: B換算数 | F3: B箱数 | G3: C換算数 | H3: C箱数 | I3: D換算数 | J3: D箱数 | K3: E換算数 | L3: E箱数
A4: =IF(販売表!A4=0,"",販売表!A4) | C4: =IF($A4="","",CEILING(販売表!C4,$B4)) | D4: =IF($A4="","",C4/$B4) | E4: =IF($A4="","",CEILING(販売表!D4,$B4)) | F4: =IF($A4="","",E4/$B4) | G4: =IF($A4="","",CEILING(販売表!E4,$B4)) | H4: =IF($A4="","",G4/$B4) | I4: =IF($A4="","",CEILING(販売表!F4,$B4)) | J4: =IF($A4="","",I4/$B4) | K4: =IF($A4="","",CEILING(販売表!G4,$B4)) | L4: =IF($A4="","",K4/$B4)
A5: =IF(販売表!A5=0,"",販売表!A5) | C5: =IF($A5="","",CEILING(販売表!C5,$B5)) | D5: =IF($A5="","",C5/$B5) | E5: =IF($A5="","",CEILING(販売表!D5,$B5)) | F5: =IF($A5="","",E5/$B5) | G5: =IF($A5="","",CEILING(販売表!E5,$B5)) | H5: =IF($A5="","",G5/$B5) | I5: =IF($A5="","",CEILING(販売表!F5,$B5)) | J5: =IF($A5="","",I5/$B5) | K5: =IF($A5="","",CEILING(販売表!G5,$B5)) | L5: =IF($A5="","",K5/$B5)
A6: =IF(販売表!A6=0,"",販売表!A6) | C6: =IF($A6="","",CEILING(販売表!C6,$B6)) | D6: =IF($A6="","",C6/$B6) | E6: =IF($A6="","",CEILING(販売表!D6,$B6)) | F6: =IF($A6="","",E6/$B6) | G6: =IF($A6="","",CEILING(販売表!E6,$B6)) | H6: =IF($A6="","",G6/$B6) | I6: =IF($A6="","",CEILING(販売表!F6,$B6)) | J6: =IF($A6="","",I6/$B6) | K6: =IF($A6="","",CEILING(販売表!G6,$B6)) | L6: =IF($A6="","",K6/$B6)
A7: =IF(販売表!A7=0,"",販売表!A7) | C7: =IF($A7="","",CEILING(販売表!C7,$B7)) | D7: =IF($A7="","",C7/$B7) | E7: =IF($A7="","",CEILING(販売表!D7,$B7)) | F7: =IF($A7="","",E7/$B7) | G7: =IF($A7="","",CEILING(販売表!E7,$B7)) | H7: =IF($A7="","",G7/$B7) | I7: =IF($A7="","",CEILING(販売表!F7,$B7)) | J7: =IF($A7="","",I7/$B7) | K7: =IF($A7="","",CEILING(販売表!G7,$B7)) | L7: =IF($A7="","",K7/$B7)
A8: =IF(販売表!A8=0,"",販売表!A8) | C8: =IF($A8="","",CEILING(販売表!C8,$B8)) | D8: =IF($A8="","",C8/$B8) | E8: =IF($A8="","",CEILING(販売表!D8,$B8)) | F8: =IF($A8="","",E8/$B8) | G8: =IF($A8="","",CEILING(販売表!E8,$B8)) | H8: =IF($A8="","",G8/$B8) | I8: =IF($A8="","",CEILING(販売表!F8,$B8)) | J8: =IF($A8="","",I8/$B8) | K8: =IF($A8="","",CEILING(販売表!G8,$B8)) | L8: =IF($A8="","",K8/$B8)
A9: =IF(販売表!A9=0,"",販売表!A9) | C9: =IF($A9="","",CEILING(販売表!C9,$B9)) | D9: =IF($A9="","",C9/$B9) | E9: =IF($A9="","",CEILING(販売表!D9,$B9)) | F9: =IF($A9="","",E9/$B9) | G9: =IF($A9="","",CEILING(販売表!E9,$B9)) | H9: =IF($A9="","",G9/$B9) | I9: =IF($A9="","",CEILING(販売表!F9,$B9)) | J9: =IF($A9="","",I9/$B9) | K9: =IF($A9="","",CEILING(販売表!G9,$B9)) | L9: =IF($A9="","",K9/$B9)
A10: =IF(販売表!A10=0,"",販売表!A10) | C10: =IF($A10="","",CEILING(販売表!C10,$B10)) | D10: =IF($A10="","",C10/$B10) | E10: =IF($A10="","",CEILING(販売表!D10,$B10)) | F10: =IF($A10="","",E10/$B10) | G10: =IF($A10="","",CEILING(販売表!E10,$B10)) | H10: =IF($A10="","",G10/$B10) | I10: =IF($A10="","",CEILING(販売表!F10,$B10)) | J10: =IF($A10="","",I10/$B10) | K10: =IF($A10="","",CEILING(販売表!G10,$B10)) | L10: =IF($A10="","",K10/$B10)
A11: =IF(販売表!A11=0,"",販売表!A11) | C11: =IF($A11="","",CEILING(販売表!C11,$B11)) | D11: =IF($A11="","",C11/$B11) | E11: =IF($A11="","",CEILING(販売表!D11,$B11)) | F11: =IF($A11="","",E11/$B11) | G11: =IF($A11="","",CEILING(販売表!E11,$B11)) | H11: =IF($A11="","",G11/$B11) | I11: =IF($A11="","",CEILING(販売表!F11,$B11)) | J11: =IF($A11="","",I11/$B11) | K11: =IF($A11="","",CEILING(販売表!G11,$B11)) | L11: =IF($A11="","",K11/$B11)
A12: =IF(販売表!A12=0,"",販売表!A12) | C12: =IF($A12="","",CEILING(販売表!C12,$B12)) | D12: =IF($A12="","",C12/$B12) | E12: =IF($A12="","",CEILING(販売表!D12,$B12)) | F12: =IF($A12="","",E12/$B12) | G12: =IF($A12="","",CEILING(販売表!E12,$B12)) | H12: =IF($A12="","",G12/$B12) | I12: =IF($A12="","",CEILING(販売表!F12,$B12)) | J12: =IF($A12="","",I12/$B12) | K12: =IF($A12="","",CEILING(販売表!G12,$B12)) | L12: =IF($A12="","",K12/$B12)
A13: =IF(販売表!A13=0,"",販売表!A13) | C13: =IF($A13="","",CEILING(販売表!C13,$B13)) | D13: =IF($A13="","",C13/$B13) | E13: =IF($A13="","",CEILING(販売表!D13,$B13)) | F13: =IF($A13="","",E13/$B13) | G13: =IF($A13="","",CEILING(販売表!E13,$B13)) | H13: =IF($A13="","",G13/$B13) | I13: =IF($A13="","",CEILING(販売表!F13,$B13)) | J13: =IF($A13="","",I13/$B13) | K13: =IF($A13="","",CEILING(販売表!G13,$B13)) | L13: =IF($A13="","",K13/$B13)
A14: =IF(販売表!A14=0,"",販売表!A14) | C14: =IF($A14="","",CEILING(販売表!C14,$B14)) | D14: =IF($A14="","",C14/$B14) | E14: =IF($A14="","",CEILING(販売表!D14,$B14)) | F14: =IF($A14="","",E14/$B14) | G14: =IF($A14="","",CEILING(販売表!E14,$B14)) | H14: =IF($A14="","",G14/$B14) | I14: =IF($A14="","",CEILING(販売表!F14,$B14)) | J14: =IF($A14="","",I14/$B14) | K14: =IF($A14="","",CEILING(販売表!G14,$B14)) | L14: =IF($A14="","",K14/$B14)
A15: =IF(販売表!A15=0,"",販売表!A15) | C15: =IF($A15="","",CEILING(販売表!C15,$B15)) | D15: =IF($A15="","",C15/$B15) | E15: =IF($A15="","",CEILING(販売表!D15,$B15)) | F15: =IF($A15="","",E15/$B15) | G15: =IF($A15="","",CEILING(販売表!E15,$B15)) | H15: =IF($A15="","",G15/$B15) | I15: =IF($A15="","",CEILING(販売表!F15,$B15)) | J15: =IF($A15="","",I15/$B15) | K15: =IF($A15="","",CEILING(販売表!G15,$B15)) | L15: =IF($A15="","",K15/$B15)
... A55: =IF(販売表!A55=0,"",販売表!A55) | C55: =IF($A55="","",CEILING(販売表!C55,$B55)) | D55: =IF($A55="","",C55/$B55) | E55: =IF($A55="","",CEILING(販売表!D55,$B55)) | F55: =IF($A55="","",E55/$B55) | G55: =IF($A55="","",CEILING(販売表!E55,$B55)) | H55: =IF($A55="","",G55/$B55) | I55: =IF($A55="","",CEILING(販売表!F55,$B55)) | J55: =IF($A55="","",I55/$B55) | K55: =IF($A55="","",CEILING(販売表!G55,$B55)) | L55: =IF($A55="","",K55/$B55)
A56: =IF(販売表!A55=0,"",販売表!A55) | C56: =IF($A56="","",CEILING(販売表!C55,$B56)) | D56: =IF($A56="","",C56/$B56) | E56: =IF($A56="","",CEILING(販売表!D55,$B56)) | F56: =IF($A56="","",E56/$B56) | G56: =IF($A56="","",CEILING(販売表!E55,$B56)) | H56: =IF($A56="","",G56/$B56) | I56: =IF($A56="","",CEILING(販売表!F55,$B56)) | J56: =IF($A56="","",I56/$B56) | K56: =IF($A56="","",CEILING(販売表!G55,$B56)) | L56: =IF($A56="","",K56/$B56)
A57: =IF(販売表!A56=0,"",販売表!A56) | C57: =IF($A57="","",CEILING(販売表!C56,$B57)) | D57: =IF($A57="","",C57/$B57) | E57: =IF($A57="","",CEILING(販売表!D56,$B57)) | F57: =IF($A57="","",E57/$B57) | G57: =IF($A57="","",CEILING(販売表!E56,$B57)) | H57: =IF($A57="","",G57/$B57) | I57: =IF($A57="","",CEILING(販売表!F56,$B57)) | J57: =IF($A57="","",I57/$B57) | K57: =IF($A57="","",CEILING(販売表!G56,$B57)) | L57: =IF($A57="","",K57/$B57)
A58: 合計 | C58: =SUM(C4:C57) -> 0 | D58: =SUM(D4:D57) -> 0 | E58: =SUM(E4:E57) -> 0 | F58: =SUM(F4:F57) -> 0 | G58: =SUM(G4:G57) -> 0 | H58: =SUM(H4:H57) -> 0 | I58: =SUM(I4:I57) -> 0 | J58: =SUM(J4:J57) -> 0 | ... L58: =SUM(L4:L57) -> 0

Sheet 箱入り数表
A1: 箱入り数表 | C1: 2026/7/1～
A2: 商品名 | B2: 箱数 | C2: 商品名 | D2: 箱数
A3: =IF(販売表!A4=0,"",販売表!A4) | C3: =IF(販売表!A31=0,"",販売表!A31)
A4: =IF(販売表!A5=0,"",販売表!A5) | C4: =IF(販売表!A32=0,"",販売表!A32)
A5: =IF(販売表!A6=0,"",販売表!A6) | C5: =IF(販売表!A33=0,"",販売表!A33)
A6: =IF(販売表!A7=0,"",販売表!A7) | C6: =IF(販売表!A34=0,"",販売表!A34)
A7: =IF(販売表!A8=0,"",販売表!A8) | C7: =IF(販売表!A35=0,"",販売表!A35)
A8: =IF(販売表!A9=0,"",販売表!A9) | C8: =IF(販売表!A36=0,"",販売表!A36)
A9: =IF(販売表!A10=0,"",販売表!A10) | C9: =IF(販売表!A37=0,"",販売表!A37)
A10: =IF(販売表!A11=0,"",販売表!A11) | C10: =IF(販売表!A38=0,"",販売表!A38)
A11: =IF(販売表!A12=0,"",販売表!A12) | C11: =IF(販売表!A39=0,"",販売表!A39)
A12: =IF(販売表!A13=0,"",販売表!A13) | C12: =IF(販売表!A40=0,"",販売表!A40)
A13: =IF(販売表!A14=0,"",販売表!A14) | C13: =IF(販売表!A41=0,"",販売表!A41)
A14: =IF(販売表!A15=0,"",販売表!A15) | C14: =IF(販売表!A42=0,"",販売表!A42)
... A29: =IF(販売表!A30=0,"",販売表!A30) | C29: =IF(販売表!A57=0,"",販売表!A57)

Sheet 計算
A1: =販売表!A1 -> 0 | E1: 計算書
B3: 単価 | C3: 営業所A | D3: A金額 | E3: 営業所B | F3: B金額 | G3: 営業所C | H3: C金額 | I3: 営業所D | J3: D金額 | K3: 営業所E | L3: E金額 | M3: 全個数 | N3: 合計金額 | O3: 限界利益単価 | P3: 限界利益
A4: =IF(販売表!A4=0,"",販売表!A4) | C4: =IF($A4="","",販売表!C4) | D4: =IF($A4="","",$B4*C4) | E4: =IF($A4="","",販売表!D4) | F4: =IF($A4="","",$B4*E4) | G4: =IF($A4="","",販売表!E4) | H4: =IF($A4="","",$B4*G4) | I4: =IF($A4="","",販売表!F4) | J4: =IF($A4="","",$B4*I4) | K4: =IF($A4="","",販売表!G4) | L4: =IF($A4="","",$B4*K4) | M4: =IF(A4="","",C4+E4+G4+I4+K4) | N4: =IF(A4="","",B4*M4) | P4: =IF(A4="","",M4*O4) | Q4: =A4
A5: =IF(販売表!A5=0,"",販売表!A5) | C5: =IF($A5="","",販売表!C5) | D5: =IF($A5="","",$B5*C5) | E5: =IF($A5="","",販売表!D5) | F5: =IF($A5="","",$B5*E5) | G5: =IF($A5="","",販売表!E5) | H5: =IF($A5="","",$B5*G5) | I5: =IF($A5="","",販売表!F5) | J5: =IF($A5="","",$B5*I5) | K5: =IF($A5="","",販売表!G5) | L5: =IF($A5="","",$B5*K5) | M5: =IF(A5="","",C5+E5+G5+I5+K5) | N5: =IF(A5="","",B5*M5) | P5: =IF(A5="","",M5*O5) | Q5: =A5
A6: =IF(販売表!A6=0,"",販売表!A6) | C6: =IF($A6="","",販売表!C6) | D6: =IF($A6="","",$B6*C6) | E6: =IF($A6="","",販売表!D6) | F6: =IF($A6="","",$B6*E6) | G6: =IF($A6="","",販売表!E6) | H6: =IF($A6="","",$B6*G6) | I6: =IF($A6="","",販売表!F6) | J6: =IF($A6="","",$B6*I6) | K6: =IF($A6="","",販売表!G6) | L6: =IF($A6="","",$B6*K6) | M6: =IF(A6="","",C6+E6+G6+I6+K6) | N6: =IF(A6="","",B6*M6) | P6: =IF(A6="","",M6*O6) | Q6: =A6
A7: =IF(販売表!A7=0,"",販売表!A7) | C7: =IF($A7="","",販売表!C7) | D7: =IF($A7="","",$B7*C7) | E7: =IF($A7="","",販売表!D7) | F7: =IF($A7="","",$B7*E7) | G7: =IF($A7="","",販売表!E7) | H7: =IF($A7="","",$B7*G7) | I7: =IF($A7="","",販売表!F7) | J7: =IF($A7="","",$B7*I7) | K7: =IF($A7="","",販売表!G7) | L7: =IF($A7="","",$B7*K7) | M7: =IF(A7="","",C7+E7+G7+I7+K7) | N7: =IF(A7="","",B7*M7) | P7: =IF(A7="","",M7*O7) | Q7: =A7
A8: =IF(販売表!A8=0,"",販売表!A8) | C8: =IF($A8="","",販売表!C8) | D8: =IF($A8="","",$B8*C8) | E8: =IF($A8="","",販売表!D8) | F8: =IF($A8="","",$B8*E8) | G8: =IF($A8="","",販売表!E8) | H8: =IF($A8="","",$B8*G8) | I8: =IF($A8="","",販売表!F8) | J8: =IF($A8="","",$B8*I8) | K8: =IF($A8="","",販売表!G8) | L8: =IF($A8="","",$B8*K8) | M8: =IF(A8="","",C8+E8+G8+I8+K8) | N8: =IF(A8="","",B8*M8) | P8: =IF(A8="","",M8*O8) | Q8: =A8
A9: =IF(販売表!A9=0,"",販売表!A9) | C9: =IF($A9="","",販売表!C9) | D9: =IF($A9="","",$B9*C9) | E9: =IF($A9="","",販売表!D9) | F9: =IF($A9="","",$B9*E9) | G9: =IF($A9="","",販売表!E9) | H9: =IF($A9="","",$B9*G9) | I9: =IF($A9="","",販売表!F9) | J9: =IF($A9="","",$B9*I9) | K9: =IF($A9="","",販売表!G9) | L9: =IF($A9="","",$B9*K9) | M9: =IF(A9="","",C9+E9+G9+I9+K9) | N9: =IF(A9="","",B9*M9) | P9: =IF(A9="","",M9*O9) | Q9: =A9
A10: =IF(販売表!A10=0,"",販売表!A10) | C10: =IF($A10="","",販売表!C10) | D10: =IF($A10="","",$B10*C10) | E10: =IF($A10="","",販売表!D10) | F10: =IF($A10="","",$B10*E10) | G10: =IF($A10="","",販売表!E10) | H10: =IF($A10="","",$B10*G10) | I10: =IF($A10="","",販売表!F10) | J10: =IF($A10="","",$B10*I10) | K10: =IF($A10="","",販売表!G10) | L10: =IF($A10="","",$B10*K10) | M10: =IF(A10="","",C10+E10+G10+I10+K10) | N10: =IF(A10="","",B10*M10) | P10: =IF(A10="","",M10*O10) | Q10: =A10
A11: =IF(販売表!A11=0,"",販売表!A11) | C11: =IF($A11="","",販売表!C11) | D11: =IF($A11="","",$B11*C11) | E11: =IF($A11="","",販売表!D11) | F11: =IF($A11="","",$B11*E11) | G11: =IF($A11="","",販売表!E11) | H11: =IF($A11="","",$B11*G11) | I11: =IF($A11="","",販売表!F11) | J11: =IF($A11="","",$B11*I11) | K11: =IF($A11="","",販売表!G11) | L11: =IF($A11="","",$B11*K11) | M11: =IF(A11="","",C11+E11+G11+I11+K11) | N11: =IF(A11="","",B11*M11) | P11: =IF(A11="","",M11*O11) | Q11: =A11
A12: =IF(販売表!A12=0,"",販売表!A12) | C12: =IF($A12="","",販売表!C12) | D12: =IF($A12="","",$B12*C12) | E12: =IF($A12="","",販売表!D12) | F12: =IF($A12="","",$B12*E12) | G12: =IF($A12="","",販売表!E12) | H12: =IF($A12="","",$B12*G12) | I12: =IF($A12="","",販売表!F12) | J12: =IF($A12="","",$B12*I12) | K12: =IF($A12="","",販売表!G12) | L12: =IF($A12="","",$B12*K12) | M12: =IF(A12="","",C12+E12+G12+I12+K12) | N12: =IF(A12="","",B12*M12) | P12: =IF(A12="","",M12*O12) | Q12: =A12
A13: =IF(販売表!A13=0,"",販売表!A13) | C13: =IF($A13="","",販売表!C13) | D13: =IF($A13="","",$B13*C13) | E13: =IF($A13="","",販売表!D13) | F13: =IF($A13="","",$B13*E13) | G13: =IF($A13="","",販売表!E13) | H13: =IF($A13="","",$B13*G13) | I13: =IF($A13="","",販売表!F13) | J13: =IF($A13="","",$B13*I13) | K13: =IF($A13="","",販売表!G13) | L13: =IF($A13="","",$B13*K13) | M13: =IF(A13="","",C13+E13+G13+I13+K13) | N13: =IF(A13="","",B13*M13) | P13: =IF(A13="","",M13*O13) | Q13: =A13
A14: =IF(販売表!A14=0,"",販売表!A14) | C14: =IF($A14="","",販売表!C14) | D14: =IF($A14="","",$B14*C14) | E14: =IF($A14="","",販売表!D14) | F14: =IF($A14="","",$B14*E14) | G14: =IF($A14="","",販売表!E14) | H14: =IF($A14="","",$B14*G14) | I14: =IF($A14="","",販売表!F14) | J14: =IF($A14="","",$B14*I14) | K14: =IF($A14="","",販売表!G14) | L14: =IF($A14="","",$B14*K14) | M14: =IF(A14="","",C14+E14+G14+I14+K14) | N14: =IF(A14="","",B14*M14) | P14: =IF(A14="","",M14*O14) | Q14: =A14
A15: =IF(販売表!A15=0,"",販売表!A15) | C15: =IF($A15="","",販売表!C15) | D15: =IF($A15="","",$B15*C15) | E15: =IF($A15="","",販売表!D15) | F15: =IF($A15="","",$B15*E15) | G15: =IF($A15="","",販売表!E15) | H15: =IF($A15="","",$B15*G15) | I15: =IF($A15="","",販売表!F15) | J15: =IF($A15="","",$B15*I15) | K15: =IF($A15="","",販売表!G15) | L15: =IF($A15="","",$B15*K15) | M15: =IF(A15="","",C15+E15+G15+I15+K15) | N15: =IF(A15="","",B15*M15) | P15: =IF(A15="","",M15*O15) | Q15: =A15
... A57: =IF(販売表!A57=0,"",販売表!A57) | C57: =IF($A57="","",販売表!C57) | D57: =IF($A57="","",$B57*C57) | E57: =IF($A57="","",販売表!D57) | F57: =IF($A57="","",$B57*E57) | G57: =IF($A57="","",販売表!E57) | H57: =IF($A57="","",$B57*G57) | I57: =IF($A57="","",販売表!F57) | J57: =IF($A57="","",$B57*I57) | K57: =IF($A57="","",販売表!G57) | L57: =IF($A57="","",$B57*K57) | M57: =IF(A57="","",C57+E57+G57+I57+K57) | N57: =IF(A57="","",B57*M57) | P57: =IF(A57="","",M57*O57) | Q57: =A57
A58: 合 計 | C58: =SUM(C4:C57) -> 0 | D58: =SUM(D4:D57) -> 0 | E58: =SUM(E4:E57) -> 0 | F58: =SUM(F4:F57) -> 0 | G58: =SUM(G4:G57) -> 0 | H58: =SUM(H4:H57) -> 0 | I58: =SUM(I4:I57) -> 0 | J58: =SUM(J4:J57) -> 0 | ... M58: =SUM(M4:M57) -> 0 | N58: =B58*M58 -> 0 | P58: =SUM(P4:P57) -> 0
C59: A合計 | E59: B合計 | G59: C合計 | I59: D合計 | K59: E合計 | M59: 総合計
G61: 営業所A | H61: 営業所B | I61: 営業所C | J61: 営業所D | K61: 営業所E | N61: 合計
G62: =D58 -> 0 | H62: =F58 -> 0 | I62: =H58 -> 0 | J62: =J58 -> 0 | K62: =L58 -> 0 | N62: =SUM(G62:M62) -> 0 | P62: 税込 | Q62: =P58*1.08 -> 0
